initialize/__init__.py
initialize/_license_template.py
initialize/_templates.py
initialize/_triggers.py
initialize/mappers.py
initialize/triggers.py
initialize/utils.py
initialize-1.1.1.dist-info/METADATA
initialize-1.1.1.dist-info/WHEEL
initialize-1.1.1.dist-info/entry_points.txt
initialize-1.1.1.dist-info/top_level.txt
initialize-1.1.1.dist-info/RECORD
