Metadata-Version: 2.1
Name: initialize
Version: 1.1.1
Summary: Automating Automation by creating automatic project structure
Home-page: https://github.com/AngrySoilder/initialize
Author: Akash Chaudhari
Author-email: chaudhari041@outlook.com
License: MIT
Keywords: standard project structure template
Platform: UNKNOWN
Classifier: License :: OSI Approved :: MIT License
Classifier: Programming Language :: Python :: 3.6
Classifier: License :: OSI Approved :: MIT License
Classifier: Programming Language :: Python
Classifier: Programming Language :: Python :: 3
Classifier: Programming Language :: Python :: 3.6
